Workbook

Sheet Summary
A1: Nxance MVP Grant Budget
A2: Reusable India master | ₹25L project envelope | ₹20L grant-cap core | Six-month prototype-to-paid-pilot plan
A4: Active scenario | B4: Full ₹25L | D4: Program cap (₹L) | E4: =Assumptions!B6 -> 20
A7: Project envelope | C7: Grant request | E7: Co-funding / extension | G7: Marketing share | I7: Duration | K7: Pilot MRR target
A8: =IF($B$4="Full ₹25L",'Scenario Compare'!B12,'Scenario Compare'!C12) -> 25 | C8: =MIN(A8,$E$4) -> 20 | E8: =MAX(A8-C8,0) -> 5 | G8: =IF($B$4="Full ₹25L",'Scenario Compare'!E10,'Scenario Compare'!F10) -> 0.1 | I8: =Assumptions!B7 -> 6 | K8: =(Assumptions!B14*Assumptions!B15)/100000 -> 0.2495
A11: Funding architecture | G11: Six-month outcome targets
A12: ₹20L grant-cap core | C12: DGX Spark + core build + testing + 10% acquisition | G12: 1 | H12: pilot-ready MVP | J12: 250 | K12: qualified beta users
A13: ₹5L extension / co-funding | C13: More specialist time, broader data, stronger acquisition and reserve | G13: 3 | H13: integrated engines | J13: 50 | K13: paying users
A14: Founder salaries | C14: Excluded | G14: 0 | H14: open critical security findings | J14: ₹24,950 | K14: starting MRR indicator
A15: Procurement rule | C15: No commitment before sanction; obtain three comparable quotes | G15: 100% | H15: traceable recommendations | J15: 6 | K15: milestone gates
A17: Selected allocation (₹L)
A18: Equipment & infrastructure | B18: =IF($B$4="Full ₹25L",'Scenario Compare'!B5,'Scenario Compare'!C5) -> 8.5
A19: External technical services | B19: =IF($B$4="Full ₹25L",'Scenario Compare'!B6,'Scenario Compare'!C6) -> 7.25
A20: Cloud, APIs & data | B20: =IF($B$4="Full ₹25L",'Scenario Compare'!B7,'Scenario Compare'!C7) -> 2.25
A21: Testing, compliance & security | B21: =IF($B$4="Full ₹25L",'Scenario Compare'!B8,'Scenario Compare'!C8) -> 1.5
A22: Pilot operations | B22: =IF($B$4="Full ₹25L",'Scenario Compare'!B9,'Scenario Compare'!C9) -> 1
A23: Pilot acquisition & marketing | B23: =IF($B$4="Full ₹25L",'Scenario Compare'!B10,'Scenario Compare'!C10) -> 2.5
A24: Controlled reserve | B24: =IF($B$4="Full ₹25L",'Scenario Compare'!B11,'Scenario Compare'!C11) -> 2

Sheet Detailed Budget
A1: Detailed MVP Costing
A2: Full and lean costs are auditable at line-item level. Full and lean totals are formula-driven.
A4: Category | B4: Item | C4: Unit | D4: Full Qty | E4: Full Unit Cost (₹L) | F4: Full Total (₹L) | G4: Lean Qty | H4: Lean Unit Cost (₹L) | I4: Lean Total (₹L) | J4: Grant treatment | K4: Work package | L4: Spend timing | M4: Source / basis | N4: Notes
A5: Editable planning caps — collect quotations and obtain incubator approval before commitment.
A6: Equipment & infrastructure | B6: NVIDIA DGX Spark — 128GB unified memory, 4TB | C6: unit | D6: 1 | E6: =ROUND((Assumptions!$B$10*Assumptions!$B$9*(1+Assumptions!$B$11)*(1+Assumptions!$B$12))/100000,2) -> 5.75 | F6: =D6*E6 -> 5.75 | G6: 1 | H6: =ROUND((Assumptions!$B$10*Assumptions!$B$9*(1+Assumptions!$B$11)*(1+Assumptions!$B$12))/100000,2) -> 5.75 | I6: =G6*H6 -> 5.75 | J6: Likely eligible; asset approval required | K6: WP1 Compute | L6: M1 | M6: Formula from official USD price, FX, GST and buffer | N6: Three quotes / GeM or authorised channel
A7: Equipment & infrastructure | B7: Linux engineering workstation — 64GB+, 2TB NVMe, mid-range GPU | C7: unit | D7: 1 | E7: 1.85 | F7: =D7*E7 -> 1.85 | G7: 1 | H7: 1.1 | I7: =G7*H7 -> 1.1 | J7: Likely eligible; asset approval required | K7: WP1 Compute | L7: M1 | M7: Planning cap; vendor quote required | N7: x86 app build, data engineering and compatibility testing
A8: Equipment & infrastructure | B8: Encrypted NAS / backup storage | C8: unit | D8: 1 | E8: 0.45 | F8: =D8*E8 -> 0.45 | G8: 1 | H8: 0.3 | I8: =G8*H8 -> 0.3 | J8: Likely eligible; asset approval required | K8: WP1 Compute | L8: M1 | M8: Planning cap | N8: Dataset versioning and backup
A9: Equipment & infrastructure | B9: UPS, secure networking and essential peripherals | C9: lot | D9: 1 | E9: 0.45 | F9: =D9*E9 -> 0.45 | G9: 1 | H9: 0.35 | I9: =G9*H9 -> 0.35 | J9: Likely eligible; asset approval required | K9: WP1 Compute | L9: M1 | M9: Planning cap | N9: Power and network continuity
A10: External technical services | B10: Short-term AI/ML engineer | C10: person-month | D10: 2.5 | E10: 1.1 | F10: =D10*E10 -> 2.75 | G10: 2 | H10: 1.1 | I10: =G10*H10 -> 2.2 | J10: Scheme-dependent service | K10: WP2 AI | L10: M2-M4 | M10: Freelancer planning rate | N10: Model evaluation, RAG and explainability
A11: External technical services | B11: Short-term full-stack/backend engineer | C11: person-month | D11: 2.5 | E11: 0.85 | F11: =D11*E11 -> 2.125 | G11: 2 | H11: 0.85 | I11: =G11*H11 -> 1.7 | J11: Scheme-dependent service | K11: WP3 Product | L11: M2-M4 | M11: Freelancer planning rate | N11: APIs, auth and application integration
A12: External technical services | B12: Short-term data engineer | C12: person-month | D12: 1.5 | E12: 0.85 | F12: =D12*E12 -> 1.275 | G12: 1 | H12: 0.9 | I12: =G12*H12 -> 0.9 | J12: Scheme-dependent service | K12: WP2 AI | L12: M2-M3 | M12: Freelancer planning rate | N12: Ingestion, normalization and test datasets
A13: External technical services | B13: UI/UX and accessibility sprint | C13: lot | D13: 1 | E13: 0.55 | F13: =D13*E13 -> 0.55 | G13: 1 | H13: 0.45 | I13: =G13*H13 -> 0.45 | J13: Scheme-dependent service | K13: WP3 Product | L13: M3-M4 | M13: Planning cap | N13: Plain-language outputs and onboarding
A14: External technical services | B14: DevOps / MLOps hardening sprint | C14: lot | D14: 1 | E14: 0.55 | F14: =D14*E14 -> 0.55 | G14: 1 | H14: 0.45 | I14: =G14*H14 -> 0.45 | J14: Scheme-dependent service | K14: WP3 Product | L14: M3-M4 | M14: Planning cap | N14: CI/CD, model registry and release controls
A15: Cloud, APIs & data | B15: Cloud burst compute / LLM evaluation APIs | C15: month | D15: 6 | E15: 0.125 | F15: =D15*E15 -> 0.75 | G15: 6 | H15: 0.075 | I15: =G15*H15 -> 0.45 | J15: Likely eligible for prototype | K15: WP2 AI | L15: M1-M6 | M15: Planning cap | N15: Use only where local compute is insufficient
A16: Cloud, APIs & data | B16: Market data and portfolio-data APIs | C16: month | D16: 6 | E16: 0.1 | F16: =D16*E16 -> 0.6 | G16: 6 | H16: 0.075 | I16: =G16*H16 -> 0.45 | J16: Likely eligible; licensing terms apply | K16: WP2 AI | L16: M1-M6 | M16: Planning cap | N16: Reference and validation data
A17: Cloud, APIs & data | B17: Observability, security and developer tools | C17: month | D17: 6 | E17: 0.075 | F17: =D17*E17 -> 0.45 | G17: 6 | H17: 0.05 | I17: =G17*H17 -> 0.3 | J17: Likely eligible for prototype | K17: WP3 Product | L17: M1-M6 | M17: Planning cap | N17: Logs, error tracking and source control
A18: Cloud, APIs & data | B18: Beta hosting and managed database | C18: month | D18: 6 | E18: 0.075 | F18: =D18*E18 -> 0.45 | G18: 6 | H18: 0.05 | I18: =G18*H18 -> 0.3 | J18: Likely eligible for trials | K18: WP4 Pilot | L18: M4-M6 | M18: Planning cap | N18: Controlled beta deployment
... A34: Controlled reserve | B34: General project risk reserve | C34: reserve | D34: 1 | E34: 0.4 | F34: =D34*E34 -> 0.4 | G34: 1 | H34: 0.3 | I34: =G34*H34 -> 0.3 | J34: Often restricted; reallocate on approval | K34: PMO | L34: Held | M34: Management reserve | N34: No founder draw
A35: TOTAL PROJECT ENVELOPE | F35: =SUM(F6:F34) -> 25 | G35: LEAN CORE | I35: =SUM(I6:I34) -> 20

Sheet Equipment
A1: Equipment and Compute Plan
A2: Each asset is tied to a specific MVP workload; figures are planning caps until quotations are received.
A4: Asset | B4: Full Cost (₹L) | C4: Lean Cost (₹L) | D4: Minimum specification | E4: MVP workload | F4: Why not cloud-only | G4: Procurement evidence | H4: Grant treatment | I4: Source URL | J4: Decision
A5: NVIDIA DGX Spark | B5: ='Detailed Budget'!F6 -> 5.75 | C5: ='Detailed Budget'!I6 -> 5.75 | D5: GB10 Grace Blackwell; 128GB unified memory; 4TB; DGX OS | E5: Local model evaluation, fine-tuning experiments, private inference and repeatable benchmarks | F5: Controls sensitive test data and reduces recurring GPU dependence | G5: Authorised vendor quote; GST; warranty; delivery; price comparison | H5: Asset approval required | I5: https://www.nvidia.com/en-in/products/workstations/dgx-spark/ | J5: Recommended
A6: Linux engineering workstation | B6: 1.85 | C6: 1.1 | D6: 64GB+ RAM; 2TB NVMe; Ubuntu; x86; mid-range CUDA GPU | E6: Data engineering, backend builds, x86 compatibility, QA and team productivity | F6: Separates application engineering from DGX model workloads | G6: Three quotes and bill of materials | H6: Asset approval required | I6: https://techtoday.lenovo.com/in/en/workstations/client-ai | J6: Recommended
A7: Encrypted NAS / backup | B7: 0.45 | C7: 0.3 | D7: Encrypted storage; snapshots; role-based access | E7: Dataset versioning, model artefacts and disaster recovery | F7: Persistent local backup is cheaper than unmanaged copies | G7: Capacity, encryption and warranty quote | H7: Asset approval required | I7: Internal specification | J7: Recommended
A8: UPS and secure network | B8: 0.45 | C8: 0.35 | D8: UPS, router/firewall, 10GbE where required | E8: Continuity, controlled access and reliable development | F8: Protects project equipment and avoids interrupted runs | G8: Rated-load and warranty quote | H8: Asset approval required | I8: Internal specification | J8: Recommended
A10: DGX Spark landed planning cost = USD 4,699 × ₹96/USD × 18% GST × 8% buffer ≈ ₹5.75L. This is not an India quotation.

Sheet Milestones
A1: Six-Month Work Plan
A2: Milestone-based delivery and disbursement gates for a prototype-to-paid-pilot grant.
A4: Month | B4: Phase | C4: Primary work | D4: Deliverable / gate | E4: Full draw (₹L) | F4: Lean draw (₹L) | G4: Selected draw (₹L) | H4: KPI | I4: Owner | J4: Evidence
A5: M1 | B5: Design & procure | C5: Architecture, data controls, benchmark plan, quotations and procurement | D5: Approved technical design and purchase orders | E5: 6 | F5: 5.5 | G5: =IF(Summary!$B$4="Full ₹25L",E5,F5) -> 6 | H5: Baseline benchmarks recorded | I5: CTO / PMO | J5: Architecture pack; quote comparison
A6: M2 | B6: Harden core | C6: Portfolio ingestion, Health Check reliability and local model environment | D6: Health Check alpha passes test dataset | E6: 4 | F6: 3.25 | G6: =IF(Summary!$B$4="Full ₹25L",E6,F6) -> 4 | H6: ≥95% import success on supported formats | I6: CTO / CIO | J6: Test report; demo build
A7: M3 | B7: Integrate engines | C7: Portfolio Builder, NxanceLM, APIs and explanation trace | D7: Three engines integrated in staging | E7: 3.75 | F7: 2.75 | G7: =IF(Summary!$B$4="Full ₹25L",E7,F7) -> 3.75 | H7: Every output linked to evidence | I7: CTO / CIO | J7: Staging release; trace audit
A8: M4 | B8: Closed alpha | C8: UX, privacy controls, MLOps, compliance boundary and alpha operations | D8: Closed alpha with 100 qualified users | E8: 3.75 | F8: 2.75 | G8: =IF(Summary!$B$4="Full ₹25L",E8,F8) -> 3.75 | H8: 100 users complete core journey | I8: CEO / COO | J8: Cohort report; counsel memo
A9: M5 | B9: Validate safely | C9: Independent QA/security, usability, beta hosting and acquisition | D9: Pilot release candidate | E9: 3.5 | F9: 2.5 | G9: =IF(Summary!$B$4="Full ₹25L",E9,F9) -> 3.5 | H9: 250 beta users; 0 open critical findings | I9: COO / CTO | J9: Security report; beta dashboard
A10: M6 | B10: Paid pilot | C10: Controlled launch, onboarding, retention measurement and grant closure | D10: Paid pilot and commercialization report | E10: 4 | F10: 3.25 | G10: =IF(Summary!$B$4="Full ₹25L",E10,F10) -> 4 | H10: 50 paying users / paid commitments | I10: CEO / COO | J10: Payment evidence; final report
A11: TOTAL | E11: =SUM(E5:E10) -> 25 | F11: =SUM(F5:F10) -> 20 | G11: =SUM(G5:G10) -> 25

Sheet Scenario Compare
A1: Scenario Comparison
A2: The ₹25L full plan and ₹20L grant-cap core use the same MVP architecture.
A4: Category | B4: Full ₹25L | C4: Lean ₹20L | D4: Difference | E4: Full % | F4: Lean % | G4: Decision implication
A5: Equipment & infrastructure | B5: =SUMIF('Detailed Budget'!$A$6:$A$34,A5,'Detailed Budget'!$F$6:$F$34) -> 8.5 | C5: =SUMIF('Detailed Budget'!$A$6:$A$34,A5,'Detailed Budget'!$I$6:$I$34) -> 7.5 | D5: =B5-C5 -> 1 | E5: =B5/$B$12 -> 0.34 | F5: =C5/$C$12 -> 0.375 | G5: DGX Spark plus complete local engineering stack
A6: External technical services | B6: =SUMIF('Detailed Budget'!$A$6:$A$34,A6,'Detailed Budget'!$F$6:$F$34) -> 7.25 | C6: =SUMIF('Detailed Budget'!$A$6:$A$34,A6,'Detailed Budget'!$I$6:$I$34) -> 5.7 | D6: =B6-C6 -> 1.55 | E6: =B6/$B$12 -> 0.29 | F6: =C6/$C$12 -> 0.285 | G6: More specialist depth and integration time
A7: Cloud, APIs & data | B7: =SUMIF('Detailed Budget'!$A$6:$A$34,A7,'Detailed Budget'!$F$6:$F$34) -> 2.25 | C7: =SUMIF('Detailed Budget'!$A$6:$A$34,A7,'Detailed Budget'!$I$6:$I$34) -> 1.5 | D7: =B7-C7 -> 0.75 | E7: =B7/$B$12 -> 0.09 | F7: =C7/$C$12 -> 0.075 | G7: More evaluation runs and data coverage
A8: Testing, compliance & security | B8: =SUMIF('Detailed Budget'!$A$6:$A$34,A8,'Detailed Budget'!$F$6:$F$34) -> 1.5 | C8: =SUMIF('Detailed Budget'!$A$6:$A$34,A8,'Detailed Budget'!$I$6:$I$34) -> 1.2 | D8: =B8-C8 -> 0.3 | E8: =B8/$B$12 -> 0.06 | F8: =C8/$C$12 -> 0.06 | G8: Independent testing remains protected
A9: Pilot operations | B9: =SUMIF('Detailed Budget'!$A$6:$A$34,A9,'Detailed Budget'!$F$6:$F$34) -> 1 | C9: =SUMIF('Detailed Budget'!$A$6:$A$34,A9,'Detailed Budget'!$I$6:$I$34) -> 0.6 | D9: =B9-C9 -> 0.4 | E9: =B9/$B$12 -> 0.04 | F9: =C9/$C$12 -> 0.03 | G9: Larger research cohort and stronger support
A10: Pilot acquisition & marketing | B10: =SUMIF('Detailed Budget'!$A$6:$A$34,A10,'Detailed Budget'!$F$6:$F$34) -> 2.5 | C10: =SUMIF('Detailed Budget'!$A$6:$A$34,A10,'Detailed Budget'!$I$6:$I$34) -> 2 | D10: =B10-C10 -> 0.5 | E10: =B10/$B$12 -> 0.1 | F10: =C10/$C$12 -> 0.1 | G10: Fixed at 10% in both scenarios
A11: Controlled reserve | B11: =SUMIF('Detailed Budget'!$A$6:$A$34,A11,'Detailed Budget'!$F$6:$F$34) -> 2 | C11: =SUMIF('Detailed Budget'!$A$6:$A$34,A11,'Detailed Budget'!$I$6:$I$34) -> 1.5 | D11: =B11-C11 -> 0.5 | E11: =B11/$B$12 -> 0.08 | F11: =C11/$C$12 -> 0.075 | G11: Held for approved variance; can be reallocated
A12: TOTAL | B12: =SUM(B5:B11) -> 25 | C12: =SUM(C5:C11) -> 20 | D12: =B12-C12 -> 5

Sheet Grant Fit
A1: Grant Route Fit
A2: Use the master deck unchanged; adapt only the ask, eligibility annexure and disallowed-cost lines for each call.
A4: Route | B4: Channel | C4: Current support | D4: Stage fit | E4: Nxance fit | F4: Recommended use | G4: Key gating item | H4: Source URL | I4: As of
A5: Startup India Seed Fund Scheme (SISFS) | B5: Approved incubator | C5: Up to ₹20L grant | D5: PoC, prototype, product trials | E5: High | F5: Apply for the ₹20L core; fund ₹5L extension separately | G5: Confirm DPIIT recognition, incorporation date, promoter holding and prior grants | H5: https://seedfund.startupindia.gov.in/faq | I5: 2026-09-02
A6: Gujarat Startup Assistance | B6: State nodal institution / incubator | C6: Up to ₹30L seed support | D6: Startup innovation and commercialization | E6: High if Gujarat-eligible | F6: Use the full ₹25L project envelope | G6: Confirm Gujarat registration, nodal route and current call | H6: https://startup.gujarat.gov.in/scheme-for-assistance/scheme-one | I6: 2026-09-02
A7: i-Hub Gujarat S4 | B7: State incubator | C7: ₹2.5–10L | D7: PoC to product / market | E7: Medium | F7: Fund one defined work package or combine with co-funding | G7: Confirm age, Gujarat link and cohort status | H7: https://ihubgujarat.in/srujan | I7: 2026-09-02
A8: MeitY TIDE 2.0 | B8: Participating ICT / university incubator | C8: Typically up to ₹7L prototype grant via incubator | D8: ICT and AI prototype | E8: Medium | F8: Fund NxanceLM, product hardening or a pilot tranche | G8: Confirm active call and incubator-specific rules | H8: https://msh.meity.gov.in/ | https://itic.iith.ac.in/ | I8: 2026-09-02
A9: NIDHI-PRAYAS 2.0 | B9: PRAYAS Centre / APC | C9: Up to ₹20L / ₹40L | D9: Physical or phygital prototypes | E9: Not eligible for pure software | F9: Do not target unless the product becomes a genuine hardware-integrated innovation | G9: Pure software and app-based solutions are expressly excluded | H9: https://nidhi-prayas.org/innovators/ | I9: 2026-09-02
A10: University incubator seed / CSR call | B10: University TBI / Section 8 incubator | C10: Call-specific | D10: Prototype and pilot | E10: High when sector and stage align | F10: Use master deck plus a scheme annexure and expense remap | G10: Confirm current call, funding source and eligible spend | H10: Incubator-specific | I10: 2026-09-02
A11: RBI / SEBI sandbox | B11: Regulatory validation | C11: Non-cash validation route | D11: Controlled fintech testing | E11: Complementary | F11: Pursue after MVP if the use case falls within regulatory scope | G11: This is validation support, not grant funding | H11: https://www.rbi.org.in/commonman/English/scripts/FAQs.aspx?Id=3822 | https://www.sebi.gov.in/sebiweb/other/RegulatorySandbox.jsp | I11: 2026-09-02

Sheet Assumptions
A1: Nxance MVP Grant Model — Assumptions
A2: Yellow cells are editable inputs. Currency inputs are in ₹ lakh unless otherwise stated. As of 2026-09-02.
A4: Driver | B4: Value | C4: Unit | D4: Source / basis | E4: Owner | F4: Notes
A5: Active scenario | B5: =Summary!B4 -> Full ₹25L | C5: scenario | D5: Selected on Summary | E5: Founder team | F5: Full ₹25L or Lean ₹20L
A6: Grant program cap | B6: 20 | C6: ₹ lakh | D6: Default SISFS grant cap; edit for target program | E6: Grant lead | F6: Project can retain a ₹25L envelope with co-funding
A7: Project duration | B7: 6 | C7: months | D7: User-selected prototype-to-pilot plan | E7: PMO | F7: Six milestone months
A8: Marketing allocation target | B8: 0.1 | C8: % of project | D8: User instruction | E8: Growth lead | F8: Held at 10% in both scenarios
A9: USD / INR planning rate | B9: 96 | C9: ₹ per USD | D9: RBI/FBIL current-rate reporting, rounded planning assumption | E9: Finance | F9: Refresh before procurement
A10: DGX Spark marketplace price | B10: 4699 | C10: USD | D10: NVIDIA US marketplace, accessed 2026-09-02 | E10: CTO | F10: India vendor quote required
A11: GST assumption | B11: 0.18 | C11: % | D11: Standard planning assumption; verify invoice treatment | E11: Finance | F11: Included in DGX landed estimate
A12: Equipment procurement buffer | B12: 0.08 | C12: % | D12: Planning allowance for shipping, FX and availability | E12: Finance | F12: Not a vendor quotation
A13: Target qualified beta users | B13: 250 | C13: users | D13: Grant KPI target | E13: Growth lead | F13: End of Month 5
A14: Target paying users | B14: 50 | C14: users | D14: Grant KPI target | E14: Growth lead | F14: End of Month 6
A15: Starting paid plan assumption | B15: 499 | C15: ₹ / month | D15: Existing Nxance pricing hypothesis | E15: CEO | F15: Used only for pilot MRR indicator
A16: Current demo users | B16: 50 | C16: users | D16: User-provided Nxance deck | E16: CEO | F16: Internal validation
A17: Investor interviews | B17: 12 | C17: interviews | D17: User-provided Nxance deck | E17: CEO | F17: Internal validation
A18: Expressed willingness to pay | B18: 8 | C18: interviews | D18: User-provided Nxance deck | E18: CEO | F18: Internal validation
A19: Project start stage | B19: Working prototype | C19: stage | D19: User-selected baseline | E19: CTO | F19: Grant turns prototype into a secure paid pilot
A20: Regulatory boundary | B20: Analytics and education first; regulated advice/execution only after approval or partnership | C20: policy | D20: Management assumption | E20: CIO | F20: Confirm with securities counsel

Sheet Checks
A1: Model Checks
A2: MODEL STATUS is PASS only when every core budget and scenario control reconciles.
A4: Check | B4: Delta / count | C4: Tolerance | D4: Status | E4: Where to fix | F4: Notes
A5: Full scenario totals ₹25L | B5: ='Scenario Compare'!B12-25 -> 0 | C5: 0.0001 | D5: =IF(ABS(B5)<=C5,"PASS","FAIL") -> PASS | E5: Detailed Budget | F5: Full total must equal 25.00
A6: Lean scenario totals ₹20L | B6: ='Scenario Compare'!C12-20 -> 0 | C6: 0.0001 | D6: =IF(ABS(B6)<=C6,"PASS","FAIL") -> PASS | E6: Detailed Budget | F6: Lean total must equal 20.00
A7: Full marketing share is 10% | B7: ='Scenario Compare'!E10-Assumptions!B8 -> 0 | C7: 0.0001 | D7: =IF(ABS(B7)<=C7,"PASS","FAIL") -> PASS | E7: Detailed Budget | F7: User-requested guardrail
A8: Lean marketing share is 10% | B8: ='Scenario Compare'!F10-Assumptions!B8 -> 0 | C8: 0.0001 | D8: =IF(ABS(B8)<=C8,"PASS","FAIL") -> PASS | E8: Detailed Budget | F8: User-requested guardrail
A9: Full milestone draws total ₹25L | B9: =Milestones!E11-25 -> 0 | C9: 0.0001 | D9: =IF(ABS(B9)<=C9,"PASS","FAIL") -> PASS | E9: Milestones | F9: Disbursement phasing control
A10: Lean milestone draws total ₹20L | B10: =Milestones!F11-20 -> 0 | C10: 0.0001 | D10: =IF(ABS(B10)<=C10,"PASS","FAIL") -> PASS | E10: Milestones | F10: Disbursement phasing control
A11: Grant request does not exceed project | B11: =MAX(Summary!C8-Summary!A8,0) -> 0 | C11: 0.0001 | D11: =IF(ABS(B11)<=C11,"PASS","FAIL") -> PASS | E11: Summary | F11: Must be zero
A12: No negative full or lean line items | B12: =COUNTIF('Detailed Budget'!$F$6:$F$34,"<0")+COUNTIF('Detailed Budget'!$I$6:$I$34,"<0") -> 0 | C12: 0 | D12: =IF(ABS(B12)<=C12,"PASS","FAIL") -> PASS | E12: Detailed Budget | F12: Count must be zero
A14: MODEL STATUS | B14: =IF(COUNTIF(D5:D12,"FAIL")=0,"PASS","FAIL") -> PASS

Sheet Sources
A1: Source Log
A2: Official URLs and internal evidence used in the budget and grant deck.
A4: ID | B4: Item | C4: Value / claim | D4: Unit | E4: As of | F4: Source type | G4: Source URL / file | H4: Used in | I4: Notes
A5: S01 | B5: DGX Spark specifications | C5: 128GB unified memory; up to 1 PFLOP FP4; 4TB | D5: spec | E5: 2026-09-02 | F5: Official vendor | G5: https://www.nvidia.com/en-in/products/workstations/dgx-spark/ | H5: Equipment; deck | I5: Use for workload justification
A6: S02 | B6: DGX Spark price | C6: 4699 | D6: USD | E6: 2026-09-02 | F6: Official marketplace | G6: https://marketplace.nvidia.com/en-us/enterprise/personal-ai-supercomputers/dgx-spark/ | H6: Assumptions; budget | I6: India quotation required
A7: S03 | B7: USD/INR planning rate | C7: 96 | D7: ₹ per USD | E7: 2026-09-02 | F7: RBI/FBIL reporting | G7: https://www.rbi.org.in/Scripts/BS_NSDPDisplay.aspx?param=4 | H7: Assumptions; budget | I7: Rounded planning rate
A8: S04 | B8: SISFS grant cap | C8: 20 | D8: ₹ lakh | E8: 2026-09-02 | F8: Official scheme | G8: https://seedfund.startupindia.gov.in/faq | H8: Grant Fit; deck | I8: Grant for PoC/prototype/product trials
A9: S05 | B9: Gujarat startup seed support | C9: 30 | D9: ₹ lakh | E9: 2026-09-02 | F9: Official state portal | G9: https://startup.gujarat.gov.in/scheme-for-assistance/scheme-one | H9: Grant Fit; deck | I9: Eligibility must be confirmed
A10: S06 | B10: i-Hub S4 support | C10: 2.5–10 | D10: ₹ lakh | E10: 2026-09-02 | F10: Official incubator | G10: https://ihubgujarat.in/srujan | H10: Grant Fit; deck | I10: PoC to product/market
A11: S07 | B11: TIDE 2.0 route | C11: Up to 7 via cited incubator | D11: ₹ lakh | E11: 2026-09-02 | F11: Official ministry/incubator | G11: https://msh.meity.gov.in/ | https://itic.iith.ac.in/ | H11: Grant Fit; deck | I11: Call-specific
A12: S08 | B12: NIDHI-PRAYAS exclusion | C12: Pure software/app solutions excluded | D12: eligibility | E12: 2026-09-02 | F12: Official program | G12: https://nidhi-prayas.org/innovators/ | H12: Grant Fit; deck | I12: Do not target for Nxance as currently framed
A13: S09 | B13: Nxance early validation | C13: 12 interviews; 8 willing to pay; 50 demo users | D13: internal | E13: User-provided | F13: User source | G13: /workspace/scratch/1529dc467b4a/upload/Nxance - Pitch Deck.pdf | H13: Deck; assumptions | I13: Validate before external submission
A14: S10 | B14: RBI IoRS | C14: Validation route, not funding | D14: route | E14: 2026-09-02 | F14: Official regulator | G14: https://www.rbi.org.in/commonman/English/scripts/FAQs.aspx?Id=3822 | H14: Grant Fit; deck | I14: Potential post-MVP pathway
A15: S11 | B15: SEBI Regulatory Sandbox | C15: Validation route, not funding | D15: route | E15: 2026-09-02 | F15: Official regulator | G15: https://www.sebi.gov.in/sebiweb/other/RegulatorySandbox.jsp | H15: Grant Fit; deck | I15: Potential post-MVP pathway
